ublkit/__init__.py
ublkit/config.py
ublkit/py.typed
ublkit/version.py
ublkit/cli/__init__.py
ublkit/cli/main.py
ublkit/core/__init__.py
ublkit/core/models.py
ublkit/core/pipeline.py
ublkit/processors/__init__.py
ublkit/processors/csv_processor.py
ublkit/processors/json_processor.py
ublkit/processors/xml_processor.py
ublkit/utils/__init__.py
ublkit/utils/decorators.py
ublkit/utils/json_flattener.py
ublkit-0.1.3.dist-info/licenses/LICENSE
ublkit-0.1.3.dist-info/METADATA
ublkit-0.1.3.dist-info/WHEEL
ublkit-0.1.3.dist-info/entry_points.txt
ublkit-0.1.3.dist-info/top_level.txt
ublkit-0.1.3.dist-info/RECORD
