Metadata-Version: 2.4
Name: ublkit
Version: 0.1.3
Summary: Simple, powerful UBL XML to JSON/CSV converter with built-in exception handling
Author-email: SherozShaikh <shaikh.sheroz07@gmail.com>
License: MIT License
Project-URL: Homepage, https://github.com/sherozshaikh/ublkit
Project-URL: Documentation, https://github.com/sherozshaikh/ublkit#readme
Project-URL: Repository, https://github.com/sherozshaikh/ublkit
Project-URL: Bug Tracker, https://github.com/sherozshaikh/ublkit/issues
Keywords: ubl,xml,json,csv,converter,invoice,e-invoicing
Classifier: Development Status :: 4 - Beta
Classifier: Intended Audience :: Developers
Classifier: License :: OSI Approved :: MIT License
Classifier: Programming Language :: Python :: 3
Classifier: Programming Language :: Python :: 3.8
Classifier: Programming Language :: Python :: 3.9
Classifier: Programming Language :: Python :: 3.10
Classifier: Programming Language :: Python :: 3.11
Classifier: Programming Language :: Python :: 3.12
Classifier: Topic :: Software Development :: Libraries :: Python Modules
Classifier: Topic :: Text Processing :: Markup :: XML
Classifier: Operating System :: OS Independent
Requires-Python: >=3.8
License-File: LICENSE
Requires-Dist: lxml>=4.9.0
Requires-Dist: polars>=0.19.0
Requires-Dist: pyyaml>=6.0
Requires-Dist: py-logex-enhanced>=0.1.0
Provides-Extra: dev
Requires-Dist: pytest>=7.0.0; extra == "dev"
Requires-Dist: pytest-cov>=4.0.0; extra == "dev"
Requires-Dist: black>=23.0.0; extra == "dev"
Requires-Dist: flake8>=6.0.0; extra == "dev"
Requires-Dist: mypy>=1.0.0; extra == "dev"
Requires-Dist: pytest-mock>=3.11.0; extra == "dev"
Requires-Dist: isort>=5.12.0; extra == "dev"
Dynamic: license-file
